atenvironment/__init__.py
atenvironment-0.2.1.dist-info/AUTHORS.rst
atenvironment-0.2.1.dist-info/LICENSE
atenvironment-0.2.1.dist-info/METADATA
atenvironment-0.2.1.dist-info/WHEEL
atenvironment-0.2.1.dist-info/top_level.txt
atenvironment-0.2.1.dist-info/RECORD
